setup.py
alchemist_armet/__init__.py
alchemist_armet/_version.py
alchemist_armet/http.py
alchemist_armet/resources.py
alchemist_armet.egg-info/PKG-INFO
alchemist_armet.egg-info/SOURCES.txt
alchemist_armet.egg-info/dependency_links.txt
alchemist_armet.egg-info/requires.txt
alchemist_armet.egg-info/top_level.txt