Metadata-Version: 1.1
Name: alchemist-armet
Version: 0.1.0
Summary: Tight integration of armet with alchemist.
Home-page: http://github.com/concordusapps/alchemist-armet
Author: Concordus Applications
Author-email: support@concordusapps.com
License: UNKNOWN
Platform: UNKNOWN
Classifier: Development Status :: 3 - Alpha
Classifier: Framework :: Flask
Classifier: Intended Audience :: Developers
Classifier: Intended Audience :: System Administrators
Classifier: License :: OSI Approved :: MIT License
Classifier: Operating System :: OS Independent
Classifier: Programming Language :: Python :: 2.7
Classifier: Programming Language :: Python :: 3.3
Classifier: Topic :: Software Development :: Libraries :: Python Modules
Classifier: Topic :: Utilities
